dmi_tcat/Tcat.py
dmi_tcat/__init__.py
dmi_tcat/models.py
dmi_tcat-0.0.5.dist-info/LICENSE
dmi_tcat-0.0.5.dist-info/METADATA
dmi_tcat-0.0.5.dist-info/WHEEL
dmi_tcat-0.0.5.dist-info/top_level.txt
dmi_tcat-0.0.5.dist-info/RECORD
