Metadata-Version: 2.1
Name: dmi-tcat
Version: 0.0.5
Summary: A little Python interface to DMI TCAT
Home-page: https://github.com/xmacex/dmi_tcat
Author: Mace Ojala
Author-email: mace.ojala@gmail.com
License: UNKNOWN
Platform: UNKNOWN
Classifier: Programming Language :: Python :: 3
Classifier: License :: OSI Approved :: GNU General Public License v3 (GPLv3)
Classifier: Operating System :: OS Independent
